polyfuzz/__init__.py
polyfuzz/error.py
polyfuzz/linkage.py
polyfuzz/metrics.py
polyfuzz/polyfuzz.py
polyfuzz/utils.py
polyfuzz/datasets/__init__.py
polyfuzz/datasets/_load_data.py
polyfuzz/models/__init__.py
polyfuzz/models/_base.py
polyfuzz/models/_distance.py
polyfuzz/models/_embeddings.py
polyfuzz/models/_gensim.py
polyfuzz/models/_rapidfuzz.py
polyfuzz/models/_sbert.py
polyfuzz/models/_spacy.py
polyfuzz/models/_tfidf.py
polyfuzz/models/_use.py
polyfuzz/models/_utils.py
polyfuzz-0.4.3.dist-info/licenses/LICENSE
tests/__init__.py
tests/test_linkage.py
tests/test_metrics.py
tests/test_polyfuzz.py
tests/utils.py
polyfuzz-0.4.3.dist-info/METADATA
polyfuzz-0.4.3.dist-info/WHEEL
polyfuzz-0.4.3.dist-info/top_level.txt
polyfuzz-0.4.3.dist-info/RECORD
