Metadata-Version: 2.4
Name: polyfuzz
Version: 0.4.3
Summary: PolyFuzz performs fuzzy string matching, grouping, and evaluation.
Home-page: https://github.com/MaartenGr/PolyFuzz
Author: Maarten Grootendorst
Author-email: maartengrootendorst@gmail.com
Project-URL: Documentation, https://maartengr.github.io/polyfuzz/
Project-URL: Source Code, https://github.com/MaartenGr/PolyFuzz/
Project-URL: Issue Tracker, https://github.com/MaartenGr/PolyFuzz/issues
Keywords: nlp string matching embeddings levenshtein tfidf bert
Classifier: Programming Language :: Python
Classifier: Intended Audience :: Science/Research
Classifier: Intended Audience :: Developers
Classifier: Topic :: Scientific/Engineering :: Artificial Intelligence
Classifier: License :: OSI Approved :: MIT License
Classifier: Topic :: Scientific/Engineering
Classifier: Operating System :: Microsoft :: Windows
Classifier: Operating System :: POSIX
Classifier: Operating System :: Unix
Classifier: Operating System :: MacOS
Classifier: Programming Language :: Python :: 3.9
Classifier: Programming Language :: Python :: 3.10
Classifier: Programming Language :: Python :: 3.11
Classifier: Programming Language :: Python :: 3.12
Requires-Python: >=3.9
License-File: LICENSE
Requires-Dist: numpy>=1.20.0
Requires-Dist: scipy>=1.3.1
Requires-Dist: pandas>=0.25.3
Requires-Dist: tqdm>=4.41.1
Requires-Dist: joblib>=0.14.0
Requires-Dist: matplotlib>=3.2.2
Requires-Dist: seaborn>=0.11.0
Requires-Dist: rapidfuzz>=0.13.1
Requires-Dist: scikit_learn>=0.22.2.post1
Provides-Extra: test
Requires-Dist: pytest>=5.4.3; extra == "test"
Requires-Dist: pytest-cov>=2.6.1; extra == "test"
Provides-Extra: docs
Requires-Dist: mkdocs==1.1; extra == "docs"
Requires-Dist: mkdocs-material==4.6.3; extra == "docs"
Requires-Dist: mkdocstrings==0.8.0; extra == "docs"
Provides-Extra: dev
Requires-Dist: mkdocs==1.1; extra == "dev"
Requires-Dist: mkdocs-material==4.6.3; extra == "dev"
Requires-Dist: mkdocstrings==0.8.0; extra == "dev"
Requires-Dist: pytest>=5.4.3; extra == "dev"
Requires-Dist: pytest-cov>=2.6.1; extra == "dev"
Requires-Dist: torch>=1.4.0; extra == "dev"
Requires-Dist: flair>=0.7; extra == "dev"
Requires-Dist: sparse_dot_topn>=0.2.9; extra == "dev"
Requires-Dist: sentence-transformers>=0.4.1; extra == "dev"
Requires-Dist: spacy>=3.0.1; extra == "dev"
Requires-Dist: tensorflow; extra == "dev"
Requires-Dist: tensorflow_hub; extra == "dev"
Requires-Dist: tensorflow_text; extra == "dev"
Provides-Extra: flair
Requires-Dist: torch>=1.4.0; extra == "flair"
Requires-Dist: flair>=0.7; extra == "flair"
Provides-Extra: fast
Requires-Dist: sparse_dot_topn>=0.2.9; extra == "fast"
Provides-Extra: sbert
Requires-Dist: sentence-transformers>=0.4.1; extra == "sbert"
Provides-Extra: use
Requires-Dist: tensorflow; extra == "use"
Requires-Dist: tensorflow_hub; extra == "use"
Requires-Dist: tensorflow_text; extra == "use"
Provides-Extra: gensim
Requires-Dist: gensim>=4.0.0; extra == "gensim"
Dynamic: author
Dynamic: author-email
Dynamic: classifier
Dynamic: description
Dynamic: description-content-type
Dynamic: home-page
Dynamic: keywords
Dynamic: license-file
Dynamic: project-url
Dynamic: provides-extra
Dynamic: requires-dist
Dynamic: requires-python
Dynamic: summary
